{
  "url": "https://api.github.com/repos/olafurpg/scalafmt/issues/190",
  "repository_url": "https://api.github.com/repos/olafurpg/scalafmt",
  "labels_url": "https://api.github.com/repos/olafurpg/scalafmt/issues/190/labels{/name}",
  "comments_url": "https://api.github.com/repos/olafurpg/scalafmt/issues/190/comments",
  "events_url": "https://api.github.com/repos/olafurpg/scalafmt/issues/190/events",
  "html_url": "https://github.com/olafurpg/scalafmt/issues/190",
  "id": 149481493,
  "number": 190,
  "title": "Scalafmt fails to format sources of sbt plugins",
  "user": {
    "login": "densh",
    "id": 320966,
    "avatar_url": "https://avatars.githubusercontent.com/u/320966?v=3",
    "gravatar_id": "",
    "url": "https://api.github.com/users/densh",
    "html_url": "https://github.com/densh",
    "followers_url": "https://api.github.com/users/densh/followers",
    "following_url": "https://api.github.com/users/densh/following{/other_user}",
    "gists_url": "https://api.github.com/users/densh/gists{/gist_id}",
    "starred_url": "https://api.github.com/users/densh/starred{/owner}{/repo}",
    "subscriptions_url": "https://api.github.com/users/densh/subscriptions",
    "organizations_url": "https://api.github.com/users/densh/orgs",
    "repos_url": "https://api.github.com/users/densh/repos",
    "events_url": "https://api.github.com/users/densh/events{/privacy}",
    "received_events_url": "https://api.github.com/users/densh/received_events",
    "type": "User",
    "site_admin": false
  },
  "labels": [
    {
      "url": "https://api.github.com/repos/olafurpg/scalafmt/labels/bug",
      "name": "bug",
      "color": "fc2929"
    }
  ],
  "state": "open",
  "locked": false,
  "assignee": null,
  "milestone": null,
  "comments": [
    {
      "url": "https://api.github.com/repos/olafurpg/scalafmt/issues/comments/218987052",
      "html_url": "https://github.com/olafurpg/scalafmt/issues/190#issuecomment-218987052",
      "issue_url": "https://api.github.com/repos/olafurpg/scalafmt/issues/190",
      "id": 218987052,
      "user": {
        "login": "olafurpg",
        "id": 1408093,
        "avatar_url": "https://avatars.githubusercontent.com/u/1408093?v=3",
        "gravatar_id": "",
        "url": "https://api.github.com/users/olafurpg",
        "html_url": "https://github.com/olafurpg",
        "followers_url": "https://api.github.com/users/olafurpg/followers",
        "following_url": "https://api.github.com/users/olafurpg/following{/other_user}",
        "gists_url": "https://api.github.com/users/olafurpg/gists{/gist_id}",
        "starred_url": "https://api.github.com/users/olafurpg/starred{/owner}{/repo}",
        "subscriptions_url": "https://api.github.com/users/olafurpg/subscriptions",
        "organizations_url": "https://api.github.com/users/olafurpg/orgs",
        "repos_url": "https://api.github.com/users/olafurpg/repos",
        "events_url": "https://api.github.com/users/olafurpg/events{/privacy}",
        "received_events_url": "https://api.github.com/users/olafurpg/received_events",
        "type": "User",
        "site_admin": false
      },
      "created_at": "2016-05-13 08:51:22 UTC",
      "updated_at": "2016-05-13 08:51:46 UTC",
      "body": "I can still reproduce on c41cbd8d96df4ed90d6da7c72030aa6759cc13ee. I wonder how many are affected.\r\n\r\nError:\r\n\r\n java.lang.NoSuchMethodError: scala.Predef$.ArrowAssoc(Ljava/lang/Object;)Ljava/lang/Object;"
    },
    {
      "url": "https://api.github.com/repos/olafurpg/scalafmt/issues/comments/219562747",
      "html_url": "https://github.com/olafurpg/scalafmt/issues/190#issuecomment-219562747",
      "issue_url": "https://api.github.com/repos/olafurpg/scalafmt/issues/190",
      "id": 219562747,
      "user": {
        "login": "dwijnand",
        "id": 344610,
        "avatar_url": "https://avatars.githubusercontent.com/u/344610?v=3",
        "gravatar_id": "",
        "url": "https://api.github.com/users/dwijnand",
        "html_url": "https://github.com/dwijnand",
        "followers_url": "https://api.github.com/users/dwijnand/followers",
        "following_url": "https://api.github.com/users/dwijnand/following{/other_user}",
        "gists_url": "https://api.github.com/users/dwijnand/gists{/gist_id}",
        "starred_url": "https://api.github.com/users/dwijnand/starred{/owner}{/repo}",
        "subscriptions_url": "https://api.github.com/users/dwijnand/subscriptions",
        "organizations_url": "https://api.github.com/users/dwijnand/orgs",
        "repos_url": "https://api.github.com/users/dwijnand/repos",
        "events_url": "https://api.github.com/users/dwijnand/events{/privacy}",
        "received_events_url": "https://api.github.com/users/dwijnand/received_events",
        "type": "User",
        "site_admin": false
      },
      "created_at": "2016-05-16 22:05:13 UTC",
      "updated_at": "2016-05-16 22:05:13 UTC",
      "body": "Probably more simply because scalaVersion is 2.10.6"
    },
    {
      "url": "https://api.github.com/repos/olafurpg/scalafmt/issues/comments/219564084",
      "html_url": "https://github.com/olafurpg/scalafmt/issues/190#issuecomment-219564084",
      "issue_url": "https://api.github.com/repos/olafurpg/scalafmt/issues/190",
      "id": 219564084,
      "user": {
        "login": "olafurpg",
        "id": 1408093,
        "avatar_url": "https://avatars.githubusercontent.com/u/1408093?v=3",
        "gravatar_id": "",
        "url": "https://api.github.com/users/olafurpg",
        "html_url": "https://github.com/olafurpg",
        "followers_url": "https://api.github.com/users/olafurpg/followers",
        "following_url": "https://api.github.com/users/olafurpg/following{/other_user}",
        "gists_url": "https://api.github.com/users/olafurpg/gists{/gist_id}",
        "starred_url": "https://api.github.com/users/olafurpg/starred{/owner}{/repo}",
        "subscriptions_url": "https://api.github.com/users/olafurpg/subscriptions",
        "organizations_url": "https://api.github.com/users/olafurpg/orgs",
        "repos_url": "https://api.github.com/users/olafurpg/repos",
        "events_url": "https://api.github.com/users/olafurpg/events{/privacy}",
        "received_events_url": "https://api.github.com/users/olafurpg/received_events",
        "type": "User",
        "site_admin": false
      },
      "created_at": "2016-05-16 22:11:16 UTC",
      "updated_at": "2016-05-16 22:11:16 UTC",
      "body": "Any suggested fix?"
    },
    {
      "url": "https://api.github.com/repos/olafurpg/scalafmt/issues/comments/219565887",
      "html_url": "https://github.com/olafurpg/scalafmt/issues/190#issuecomment-219565887",
      "issue_url": "https://api.github.com/repos/olafurpg/scalafmt/issues/190",
      "id": 219565887,
      "user": {
        "login": "dwijnand",
        "id": 344610,
        "avatar_url": "https://avatars.githubusercontent.com/u/344610?v=3",
        "gravatar_id": "",
        "url": "https://api.github.com/users/dwijnand",
        "html_url": "https://github.com/dwijnand",
        "followers_url": "https://api.github.com/users/dwijnand/followers",
        "following_url": "https://api.github.com/users/dwijnand/following{/other_user}",
        "gists_url": "https://api.github.com/users/dwijnand/gists{/gist_id}",
        "starred_url": "https://api.github.com/users/dwijnand/starred{/owner}{/repo}",
        "subscriptions_url": "https://api.github.com/users/dwijnand/subscriptions",
        "organizations_url": "https://api.github.com/users/dwijnand/orgs",
        "repos_url": "https://api.github.com/users/dwijnand/repos",
        "events_url": "https://api.github.com/users/dwijnand/events{/privacy}",
        "received_events_url": "https://api.github.com/users/dwijnand/received_events",
        "type": "User",
        "site_admin": false
      },
      "created_at": "2016-05-16 22:20:09 UTC",
      "updated_at": "2016-05-16 22:20:09 UTC",
      "body": "Less hacks, more cross-building :)"
    }
  ],
  "created_at": "2016-04-19 14:41:29 UTC",
  "updated_at": "2016-05-16 22:20:09 UTC",
  "closed_at": null,
  "body": "Reproduction:\r\nhttps://github.com/densh/sbt-plugin-scalafmt-failure\r\n\r\nUsing\r\n* 0.2.4-RC1"
}